lcls_naming_tool/__init__.py
lcls_naming_tool/_version.py
lcls_naming_tool/lcls_naming_tool.py
lcls_naming_tool/version.py
lcls_naming_tool/bin/__init__.py
lcls_naming_tool/bin/help.py
lcls_naming_tool/bin/main.py
lcls_naming_tool/taxons/ccc_taxon.json
lcls_naming_tool/taxons/functional_component_taxon.json
lcls_naming_tool/taxons/fungible_element_taxon.json
lcls_naming_tool/tests/__init__.py
lcls_naming_tool/tests/conftest.py
lcls_naming_tool/tests/test_cli.py
lcls_naming_tool/web/app.py
lcls_naming_tool/web/gunicorn_config.py
lcls_naming_tool/web/templates/base.html
lcls_naming_tool/web/templates/index.html
lcls_naming_tool-1.0.1.dist-info/AUTHORS.rst
lcls_naming_tool-1.0.1.dist-info/LICENSE
lcls_naming_tool-1.0.1.dist-info/METADATA
lcls_naming_tool-1.0.1.dist-info/WHEEL
lcls_naming_tool-1.0.1.dist-info/entry_points.txt
lcls_naming_tool-1.0.1.dist-info/top_level.txt
lcls_naming_tool-1.0.1.dist-info/RECORD
